semisupervised/LabelPropagation.py
semisupervised/LabelSpreading.py
semisupervised/__init__.py
supervised/KNN.py
supervised/__init__.py
unsupervised/DBSCAN.py
unsupervised/Isomap.py
unsupervised/UMAP.py
unsupervised/__init__.py
adaptive_ml-0.1.4.dist-info/METADATA
adaptive_ml-0.1.4.dist-info/WHEEL
adaptive_ml-0.1.4.dist-info/top_level.txt
adaptive_ml-0.1.4.dist-info/RECORD
