Metadata-Version: 2.4
Name: adaptive_ml
Version: 0.1.4
Summary: A collection of adaptive machine learning algorithms for clustering.
Author: Andreotti Stefano
Author-email: andreotti.stefano.sa@gmail.com
Classifier: Development Status :: 3 - Alpha
Classifier: Intended Audience :: Developers
Classifier: License :: OSI Approved :: MIT License
Classifier: Programming Language :: Python :: 3.9
Requires-Dist: numpy>=1.26.4
Requires-Dist: scikit_learn>=1.6.1
Requires-Dist: scipy>=1.13.1
Requires-Dist: setuptools>=75.8.0
Requires-Dist: umap_learn>=0.5.7
Dynamic: author
Dynamic: author-email
Dynamic: classifier
Dynamic: requires-dist
Dynamic: summary
